anubisgit/__init__.py
anubisgit/anubisgit_time_machine.yml
anubisgit/authors.py
anubisgit/cli.py
anubisgit/color_tools.py
anubisgit/comparator.py
anubisgit/data_loader.py
anubisgit/datetime_tools.py
anubisgit/external_analysis.py
anubisgit/git_helpers.py
anubisgit/graph_tools.py
anubisgit/joindb.py
anubisgit/list_tools.py
anubisgit/plot_activity.py
anubisgit/plot_blame.py
anubisgit/plot_blame_html.py
anubisgit/plot_branches.py
anubisgit/plot_branches_html.py
anubisgit/plot_common.py
anubisgit/plot_complexity.py
anubisgit/plot_complexity_html.py
anubisgit/pyplot_tools.py
anubisgit/timegraph.py
anubisgit/timemachine.py
anubisgit-0.7.0.dist-info/METADATA
anubisgit-0.7.0.dist-info/WHEEL
anubisgit-0.7.0.dist-info/entry_points.txt
anubisgit-0.7.0.dist-info/top_level.txt
anubisgit-0.7.0.dist-info/RECORD
