Metadata-Version: 2.1
Name: anubisgit
Version: 0.7.0
Summary: Anubis, a CodeMetrics helper
Home-page: https://gitlab.com/cerfacs/anubisgit
Author: CoopTeam-CERFACS
Author-email: coop@cerfacs.com
Project-URL: Homepage, https://gitlab.com/cerfacs/anubisgit
Project-URL: Documentation, https://anubisgit.readthedocs.io/en/latest/
Project-URL: Bug Tracker, https://gitlab.com/cerfacs/anubisgit/-/issues
Keywords: code metrics,code analysis
Classifier: Programming Language :: Python :: 3.7
Classifier: Programming Language :: Python :: 3.8
Classifier: Programming Language :: Python :: 3.9
Classifier: Programming Language :: Python :: 3.10
Classifier: Programming Language :: Python :: 3.11
Classifier: License :: OSI Approved :: MIT License
Requires-Python: >=3.7
Requires-Dist: click
Requires-Dist: tucan >=0.4.5
Requires-Dist: pyyaml
Requires-Dist: python-Levenshtein
Requires-Dist: python-dateutil
Requires-Dist: numpy
Requires-Dist: matplotlib
Requires-Dist: plotly
Requires-Dist: seaborn
Requires-Dist: pathlib
Requires-Dist: loguru
Requires-Dist: tol-colors
Provides-Extra: docs
Requires-Dist: myst-parser ; extra == 'docs'
Requires-Dist: sphinx-rtd-theme ; extra == 'docs'
Provides-Extra: tests
Requires-Dist: pytest ; extra == 'tests'
Requires-Dist: pytest-coverage ; extra == 'tests'
Requires-Dist: pytest-allclose ; extra == 'tests'
Requires-Dist: pytest-mock ; extra == 'tests'
